extendedseleniumpagefactory/__init__.py
extendedseleniumpagefactory/extendedpagefactory.py
extended_selenium_page_factory-0.7b0.dist-info/METADATA
extended_selenium_page_factory-0.7b0.dist-info/WHEEL
extended_selenium_page_factory-0.7b0.dist-info/top_level.txt
extended_selenium_page_factory-0.7b0.dist-info/RECORD
